{"assets/images/Abhay.jpg":["assets/images/Abhay.jpg"],"assets/images/Abhijat.jpg":["assets/images/Abhijat.jpg"],"assets/images/Aditya.jpg":["assets/images/Aditya.jpg"],"assets/images/Amit.jpg":["assets/images/Amit.jpg"],"assets/images/AnanyaV1.jpg":["assets/images/AnanyaV1.jpg"],"assets/images/AnanyaV2.jpg":["assets/images/AnanyaV2.jpg"],"assets/images/Arnav.jpg":["assets/images/Arnav.jpg"],"assets/images/Aryamaan.jpg":["assets/images/Aryamaan.jpg"],"assets/images/Asmi.jpg":["assets/images/Asmi.jpg"],"assets/images/Ayushmaan.jpg":["assets/images/Ayushmaan.jpg"],"assets/images/Bhumi.jpg":["assets/images/Bhumi.jpg"],"assets/images/Chinmay.jpg":["assets/images/Chinmay.jpg"],"assets/images/Dev.jpg":["assets/images/Dev.jpg"],"assets/images/Dhruvi.jpg":["assets/images/Dhruvi.jpg"],"assets/images/Hari.jpg":["assets/images/Hari.jpg"],"assets/images/Harsh.jpg":["assets/images/Harsh.jpg"],"assets/images/Kanika.jpg":["assets/images/Kanika.jpg"],"assets/images/Mahesh.jpg":["assets/images/Mahesh.jpg"],"assets/images/Manan.jpg":["assets/images/Manan.jpg"],"assets/images/Manish.jpg":["assets/images/Manish.jpg"],"assets/images/Panav.jpg":["assets/images/Panav.jpg"],"assets/images/Pranav.jpg":["assets/images/Pranav.jpg"],"assets/images/Prathmesh.jpg":["assets/images/Prathmesh.jpg"],"assets/images/Priyam.jpg":["assets/images/Priyam.jpg"],"assets/images/Rakshit.jpg":["assets/images/Rakshit.jpg"],"assets/images/Ritesh.jpg":["assets/images/Ritesh.jpg"],"assets/images/Ronak.jpg":["assets/images/Ronak.jpg"],"assets/images/Sajjad.jpg":["assets/images/Sajjad.jpg"],"assets/images/Satyam.jpg":["assets/images/Satyam.jpg"],"assets/images/Senjeet.jpg":["assets/images/Senjeet.jpg"],"assets/images/Shaurya.jpg":["assets/images/Shaurya.jpg"],"assets/images/Shivtej.jpg":["assets/images/Shivtej.jpg"],"assets/images/Sreehari.jpg":["assets/images/Sreehari.jpg"],"assets/images/Tanmay.jpg":["assets/images/Tanmay.jpg"],"assets/images/Tarus.jpg":["assets/images/Tarus.jpg"],"assets/images/Vaibhav.jpg":["assets/images/Vaibhav.jpg"],"assets/images/Vidit.jpg":["assets/images/Vidit.jpg"],"assets/images/Vivek.jpg":["assets/images/Vivek.jpg"],"packages/cupertino_icons/assets/CupertinoIcons.ttf":["packages/cupertino_icons/assets/CupertinoIcons.ttf"]}